{
   "data": [
      {
         "name": "The Loyal We @ Rainy Day Bookstore and Cafe",
         "start_time": "2010-04-29T01:30:00+0000",
         "end_time": "2010-04-29T04:30:00+0000",
         "location": "Nishi Azabu",
         "id": "116600818359630"
      },
      {
         "name": "Smart Day 1 in \u9280\u5ea7",
         "start_time": "2010-04-02T02:00:00+0000",
         "end_time": "2010-04-02T03:00:00+0000",
         "location": "\u9280\u5ea7\u3000\u30a2\u30c3\u30d7\u30eb\u30b9\u30c8\u30a2",
         "id": "365881598945"
      },
      {
         "name": "Tokyo 2.0 #31 - Mobile Web Convergence",
         "start_time": "2010-02-09T03:00:00+0000",
         "end_time": "2010-02-09T06:00:00+0000",
         "location": "Super-Deluxe (www.super-deluxe.com)",
         "id": "238616194462"
      },
      {
         "name": "Hello 33. Sayonara Tokyo.",
         "start_time": "2010-01-24T04:00:00+0000",
         "end_time": "2010-01-24T16:00:00+0000",
         "location": "Opus Aobadai #602 (Castelo Esperanto)",
         "id": "256812599701"
      },
      {
         "name": "Tokyo 2.0 #29 - Web Fair / \u30a6\u30a7\u30d6\u30d5\u30a7\u30a2",
         "start_time": "2009-10-20T02:00:00+0000",
         "end_time": "2009-10-20T05:30:00+0000",
         "location": "Super-Deluxe (www.super-deluxe.com)",
         "id": "158972432609"
      },
      {
         "name": "Housewarming",
         "start_time": "2009-06-13T22:00:00+0000",
         "end_time": "2009-06-14T06:00:00+0000",
         "location": "\u30b9\u30bf\u30fc\u30f4\u30a1\u30ec\u30a4II\uff12\uff10\uff13\u53f7\u5ba4",
         "id": "99852142058"
      },
      {
         "name": "RailsConf 2009",
         "start_time": "2009-05-04T16:00:00+0000",
         "end_time": "2009-05-08T00:00:00+0000",
         "location": "Las Vegas Hilton",
         "id": "35430263075"
      },
      {
         "name": "Tokyo 2.0 #23 (April 13 2009) - The Sustainable Web (\u30a6\u30a8\u30d6\u3068\u30a8\u30b3)",
         "start_time": "2009-04-14T01:30:00+0000",
         "end_time": "2009-04-14T06:00:00+0000",
         "location": "Super Deluxe (www.super-deluxe.com)",
         "id": "70871098149"
      },
      {
         "name": "Tokyo 2.0 #21 - Open Social App Dev & kakuteru.com",
         "start_time": "2009-02-10T03:00:00+0000",
         "end_time": "2009-02-10T06:00:00+0000",
         "location": "Super Deluxe (www.super-deluxe.com)",
         "id": "62495467768"
      }
   ],
   "paging": {
      "previous": "https://graph.facebook.com/579612276/events?access_token=2227470867%7C2.R9XAeEGAiuhhRCcZAgJzTA__.3600.1272362400-579612276%7ChajPs3sLZ2opsOA9TSEGEq-lBrE.&limit=25&since=2010-04-29T01%3A30%3A00%2B0000",
      "next": "https://graph.facebook.com/579612276/events?access_token=2227470867%7C2.R9XAeEGAiuhhRCcZAgJzTA__.3600.1272362400-579612276%7ChajPs3sLZ2opsOA9TSEGEq-lBrE.&limit=25&until=2009-02-10T03%3A00%3A00%2B0000"
   }
}